routheon_server/__init__.py
routheon_server/__main__.py
routheon_server/_version.py
routheon_server/aggregator.py
routheon_server/cli.py
routheon_server/config.py
routheon_server/logging_setup.py
routheon_server/mappings.py
routheon_server/models.py
routheon_server/server.py
routheon_server/stats.py
routheon_server-1.0.7.dist-info/METADATA
routheon_server-1.0.7.dist-info/WHEEL
routheon_server-1.0.7.dist-info/entry_points.txt
routheon_server-1.0.7.dist-info/licenses/LICENSE
routheon_server-1.0.7.dist-info/RECORD
