Metadata-Version: 2.4
Name: routheon-server
Version: 1.0.7
Summary: Expose OpenAI-compatible /v1/models aggregation plus /stats host metrics behind Traefik.
Project-URL: Homepage, https://github.com/Wuodan/routheon
Project-URL: Repository, https://github.com/Wuodan/routheon
Project-URL: Issues, https://github.com/Wuodan/routheon/issues
License: Apache-2.0
License-File: LICENSE
Requires-Python: >=3.10
Requires-Dist: psutil
Requires-Dist: pyyaml
